pytest_smart_debugger_server/__init__.py
pytest_smart_debugger_server/apply_patch.py
pytest_smart_debugger_server/completion_model.py
pytest_smart_debugger_server/generate_prompt.py
pytest_smart_debugger_server/llm_interface.py
pytest_smart_debugger_server/process_debug_info.py
pytest_smart_debugger_server/server.py
pytest_smart_debugger_backend-0.0.3.dist-info/METADATA
pytest_smart_debugger_backend-0.0.3.dist-info/WHEEL
pytest_smart_debugger_backend-0.0.3.dist-info/entry_points.txt
pytest_smart_debugger_backend-0.0.3.dist-info/top_level.txt
pytest_smart_debugger_backend-0.0.3.dist-info/RECORD
