Metadata-Version: 2.4
Name: pytest-smart-debugger-backend
Version: 0.0.3
Summary: Backend server for Pytest Smart Debugger
Author: Tymofii Shchetilin
Requires-Python: >=3.8
